Metadata-Version: 2.1
Name: paquete_prueba_rms
Version: 1.0
Summary: paquete de suma y resta
Author: Richard Makiya
